xpw_locker/__init__.py
xpw_locker/attribute.py
xpw_locker/httpproxy.py
xpw_locker/sockproxy.py
xpw_locker/resources/__init__.py
xpw_locker/resources/favicon.ico
xpw_locker/resources/locked.ico
xpw_locker/resources/login.html
xpw_locker/resources/unlock.ico
xpw_locker/resources/images/__init__.py
xpw_locker/resources/images/logo-locked.svg
xpw_locker/resources/images/logo-unlock.svg
xpw_locker/resources/images/logo.svg
xpw_locker/resources/translate/__init__.py
xpw_locker/resources/translate/en.xlc
xpw_locker/resources/translate/zh-Hans.xlc
xpw_locker/resources/translate/zh-Hant.xlc
xpw_locker-1.0.1.dist-info/LICENSE
xpw_locker-1.0.1.dist-info/METADATA
xpw_locker-1.0.1.dist-info/WHEEL
xpw_locker-1.0.1.dist-info/entry_points.txt
xpw_locker-1.0.1.dist-info/top_level.txt
xpw_locker-1.0.1.dist-info/zip-safe
xpw_locker-1.0.1.dist-info/RECORD
