Metadata-Version: 2.1
Name: xpw-locker
Version: 1.0.1
Summary: Access authentication
Home-page: https://github.com/checkeys/locker/
Author: Mingzhe Zou
Author-email: zoumingzhe@outlook.com
License: GPLv2
Project-URL: Source Code, https://github.com/checkeys/locker/
Project-URL: Bug Tracker, https://github.com/checkeys/locker/issues
Project-URL: Documentation, https://github.com/checkeys/locker/
Keywords: command-line,argparse,argcomplete
Platform: any
Classifier: Programming Language :: Python
Classifier: Programming Language :: Python :: 3
Requires-Python: >=3.8
License-File: LICENSE
Requires-Dist: xkits-command >=0.5.3
Requires-Dist: xkits-thread >=0.2
Requires-Dist: xkits-lib >=0.4
Requires-Dist: xhtm >=0.12.1
Requires-Dist: xser >=0.5.1
Requires-Dist: xpw >=0.14
